pycryptosimple_aes/__init__.py
pycryptosimple_aes/main.py
pycryptosimple_aes-1.1.dist-info/LICENSE
pycryptosimple_aes-1.1.dist-info/METADATA
pycryptosimple_aes-1.1.dist-info/WHEEL
pycryptosimple_aes-1.1.dist-info/top_level.txt
pycryptosimple_aes-1.1.dist-info/RECORD
