Metadata-Version: 2.1
Name: pycryptosimple-aes
Version: 1.1
Home-page: https://github.com/AndreasKarageorgos/simpleAES
Author: Andreas Karageorgos
License: MIT
License-File: LICENSE
Requires-Dist: pycryptodome
